GameData/Exceptions.py
GameData/GameDataControllers.py
GameData/__init__.py
EasyGameTools-0.1.2.dist-info/LICENSE
EasyGameTools-0.1.2.dist-info/METADATA
EasyGameTools-0.1.2.dist-info/WHEEL
EasyGameTools-0.1.2.dist-info/top_level.txt
EasyGameTools-0.1.2.dist-info/RECORD
