Metadata-Version: 2.1
Name: EasyGameTools
Version: 0.1.2
Summary: Makes developing games and handling data easy
Home-page: https://ajtechcity.com
Author: Arun Dutta-Plummer
Author-email: arunjai12456@gmail.com
License: GPL-3.0
Platform: UNKNOWN
Classifier: Programming Language :: Python :: 3
Classifier: License :: OSI Approved :: MIT License
Classifier: Operating System :: OS Independent
License-File: LICENSE
Requires-Dist: cryptography
